mycalc/calculator.py
carusina01-0.0.1.dist-info/METADATA
carusina01-0.0.1.dist-info/WHEEL
carusina01-0.0.1.dist-info/top_level.txt
carusina01-0.0.1.dist-info/RECORD
