Metadata-Version: 2.1
Name: carusina01
Version: 0.0.1
Summary: oss-dev my calculator 0001
Home-page: https://github.com/carusina/calc0001
Download-URL: https://github.com/carusina/calc0001
Author: carusina
Author-email: msjjang0315@naver.com
License: UNKNOWN
Platform: UNKNOWN
Classifier: Programming Language :: Python :: 3
